arcade_engine_api/__init__.py
arcade_engine_api/tools/__init__.py
arcade_engine_api/tools/request_body_schemas.py
arcade_engine_api/wrapper_tools/AuthorizeUserToolAccess.json
arcade_engine_api/wrapper_tools/AuthorizeWorker.json
arcade_engine_api/wrapper_tools/CheckArcadeEngineHealth.json
arcade_engine_api/wrapper_tools/CheckAuthStatus.json
arcade_engine_api/wrapper_tools/ConfirmUserAuthentication.json
arcade_engine_api/wrapper_tools/CreateAuthProvider.json
arcade_engine_api/wrapper_tools/CreateWorker.json
arcade_engine_api/wrapper_tools/DeleteAuthProvider.json
arcade_engine_api/wrapper_tools/DeleteMcpEndpoint.json
arcade_engine_api/wrapper_tools/DeleteSecretById.json
arcade_engine_api/wrapper_tools/DeleteUserAuthConnection.json
arcade_engine_api/wrapper_tools/DeleteWorker.json
arcade_engine_api/wrapper_tools/ExecuteTool.json
arcade_engine_api/wrapper_tools/FetchToolsPage.json
arcade_engine_api/wrapper_tools/GetAuthProviderDetails.json
arcade_engine_api/wrapper_tools/GetEngineConfiguration.json
arcade_engine_api/wrapper_tools/GetFormattedToolSpecification.json
arcade_engine_api/wrapper_tools/GetModelContextProtocol.json
arcade_engine_api/wrapper_tools/GetProjectDetails.json
arcade_engine_api/wrapper_tools/GetScheduledToolDetails.json
arcade_engine_api/wrapper_tools/GetScheduledToolExecutions.json
arcade_engine_api/wrapper_tools/GetSessionVerificationSettings.json
arcade_engine_api/wrapper_tools/GetSwaggerSpecification.json
arcade_engine_api/wrapper_tools/GetToolSpecification.json
arcade_engine_api/wrapper_tools/GetToolsList.json
arcade_engine_api/wrapper_tools/GetWorkerById.json
arcade_engine_api/wrapper_tools/GetWorkerHealthStatus.json
arcade_engine_api/wrapper_tools/ListAccessibleProjects.json
arcade_engine_api/wrapper_tools/ListAuthConnections.json
arcade_engine_api/wrapper_tools/ListAvailableAuthProviders.json
arcade_engine_api/wrapper_tools/ListVisibleSecrets.json
arcade_engine_api/wrapper_tools/ListWorkers.json
arcade_engine_api/wrapper_tools/ManageSecret.json
arcade_engine_api-0.1.0.dist-info/METADATA
arcade_engine_api-0.1.0.dist-info/WHEEL
arcade_engine_api-0.1.0.dist-info/entry_points.txt
arcade_engine_api-0.1.0.dist-info/licenses/LICENSE
arcade_engine_api-0.1.0.dist-info/RECORD
